odoo/addons/product_supplierinfo_comment/README.rst
odoo/addons/product_supplierinfo_comment/__init__.py
odoo/addons/product_supplierinfo_comment/__manifest__.py
odoo/addons/product_supplierinfo_comment/i18n/es.po
odoo/addons/product_supplierinfo_comment/i18n/product_supplierinfo_comment.pot
odoo/addons/product_supplierinfo_comment/models/__init__.py
odoo/addons/product_supplierinfo_comment/models/product_supplierinfo.py
odoo/addons/product_supplierinfo_comment/readme/CONTRIBUTORS.rst
odoo/addons/product_supplierinfo_comment/readme/DESCRIPTION.rst
odoo/addons/product_supplierinfo_comment/static/description/icon.png
odoo/addons/product_supplierinfo_comment/static/description/index.html
odoo/addons/product_supplierinfo_comment/views/product_views.xml
odoo_addon_product_supplierinfo_comment-15.0.1.0.0.1.dist-info/METADATA
odoo_addon_product_supplierinfo_comment-15.0.1.0.0.1.dist-info/WHEEL
odoo_addon_product_supplierinfo_comment-15.0.1.0.0.1.dist-info/top_level.txt
odoo_addon_product_supplierinfo_comment-15.0.1.0.0.1.dist-info/RECORD
